[{"photo": {"id": "27874258870", "secret": "36ce85b141", "server": "7531", "farm": 8, "owner": {"nsid": "126576977@N07", "username": "Pfalzknipser", "realname": "", "iconserver": "1494", "iconfarm": 2}, "title": {"_content": "In der Vorderpfalz"}, "views": "1141", "comments": {"_content": "2"}, "tags": {"tag": [{"id": "126555647-27874258870-1637257", "raw": "Kulturlandschaft", "_content": "kulturlandschaft"}, {"id": "126555647-27874258870-3936072", "raw": "Lichtstimmung", "_content": "lichtstimmung"}, {"id": "126555647-27874258870-128325319", "raw": "Mittelhardt", "_content": "mittelhardt"}]}, "favpersons": [{"nsid": "60571553@N07", "username": "sascha-laessig-fotografie.de", "realname": "Sascha L\u00e4ssig", "favedate": "1484642821", "iconserver": "3900", "iconfarm": 4, "contact": 0, "friend": 0, "family": 0}, {"nsid": "143254993@N06", "username": "tanjatall", "realname": "Tatjana Olsson", "favedate": "1479398705", "iconserver": "262", "iconfarm": 1, "contact": 0, "friend": 0, "family": 0}, {"nsid": "145029501@N04", "username": "Laura Cerullo", "realname": "Laura Cerullo", "favedate": "1479395094", "iconserver": "5788", "iconfarm": 6, "contact": 0, "friend": 0, "family": 0}, {"nsid": "68221479@N00", "username": "RB PhotoVisions", "realname": "Robert Bonsels", "favedate": "1476177318", "iconserver": "7109", "iconfarm": 8, "contact": 0, "friend": 0, "family": 0}, {"nsid": "127997011@N03", "username": "R\u00e4i", "realname": "R\u00e4i", "favedate": "1475683892", "iconserver": "663", "iconfarm": 1, "contact": 0, "friend": 0, "family": 0}, {"nsid": "94340476@N04", "username": "MC-80", "realname": "", "favedate": "1475002799", "iconserver": "7447", "iconfarm": 8, "contact": 0, "friend": 0, "family": 0}, {"nsid": "143926882@N07", "username": "christiannass", "realname": "Christian Nass", "favedate": "1472648462", "iconserver": "7510", "iconfarm": 8, "contact": 0, "friend": 0, "family": 0}, {"nsid": "135762220@N06", "username": "redfurwolf", "realname": "Martin Wolf", "favedate": "1471188070", "iconserver": "627", "iconfarm": 1, "contact": 0, "friend": 0, "family": 0}, {"nsid": "74798663@N02", "username": "WiSch | Foto", "realname": "", "favedate": "1468833477", "iconserver": "4701", "iconfarm": 5, "contact": 0, "friend": 0, "family": 0}, {"nsid": "144714665@N04", "username": "Lini;-)", "realname": "", "favedate": "1468777983", "iconserver": "4278", "iconfarm": 5, "contact": 0, "friend": 0, "family": 0}], "faves": 19}, "stat": "ok"}, {"photo": {"id": "27842366555", "secret": "5b42b3f977", "server": "7664", "farm": 8, "owner": {"nsid": "126576977@N07", "username": "Pfalzknipser", "realname": "", "iconserver": "1494", "iconfarm": 2}, "title": {"_content": "In der Pfalz"}, "views": "15569", "comments": {"_content": "13"}, "tags": {"tag": [{"id": "126555647-27842366555-184414", "raw": "Kornfeld", "_content": "kornfeld"}, {"id": "126555647-27842366555-1637257", "raw": "Kulturlandschaft", "_content": "kulturlandschaft"}, {"id": "126555647-27842366555-3936072", "raw": "Lichtstimmung", "_content": "lichtstimmung"}]}, "favpersons": [{"nsid": "47134714@N04", "username": "fossiled", "realname": "Ed", "favedate": "1516917877", "iconserver": "7584", "iconfarm": 8, "contact": 0, "friend": 0, "family": 0}, {"nsid": "147619422@N07", "username": "Berto Blanco \u263c", "realname": "Humberto Blanco", "favedate": "1487830620", "iconserver": "3947", "iconfarm": 4, "contact": 0, "friend": 0, "family": 0}, {"nsid": "98881729@N04", "username": "ludderz", "realname": "David Ludman", "favedate": "1483711024", "iconserver": "8797", "iconfarm": 9, "contact": 0, "friend": 0, "family": 0}, {"nsid": "143254993@N06", "username": "tanjatall", "realname": "Tatjana Olsson", "favedate": "1479398919", "iconserver": "262", "iconfarm": 1, "contact": 0, "friend": 0, "family": 0}, {"nsid": "94340476@N04", "username": "MC-80", "realname": "", "favedate": "1475002820", "iconserver": "7447", "iconfarm": 8, "contact": 0, "friend": 0, "family": 0}, {"nsid": "129896023@N05", "username": "photography_myriam", "realname": "", "favedate": "1469216932", "iconserver": "4181", "iconfarm": 5, "contact": 0, "friend": 0, "family": 0}, {"nsid": "135638490@N03", "username": "Jacques Teller", "realname": "Jacques Teller", "favedate": "1468564633", "iconserver": "4466", "iconfarm": 5, "contact": 0, "friend": 0, "family": 0}, {"nsid": "90534814@N05", "username": "Brandon_Hilder", "realname": "Brandon Hilder", "favedate": "1468554365", "iconserver": "7097", "iconfarm": 8, "contact": 0, "friend": 0, "family": 0}, {"nsid": "9535010@N04", "username": "Adventurer Dustin Holmes", "realname": "Dustin Holmes", "favedate": "1468045993", "iconserver": "3942", "iconfarm": 4, "contact": 0, "friend": 0, "family": 0}, {"nsid": "32505559@N00", "username": "Rene Wieland", "realname": "", "favedate": "1467891052", "iconserver": "7530", "iconfarm": 8, "contact": 0, "friend": 0, "family": 0}], "faves": 362}, "stat": "ok"}, {"photo": {"id": "28234998854", "secret": "52cbddb394", "server": "8224", "farm": 9, "owner": {"nsid": "126576977@N07", "username": "Pfalzknipser", "realname": "", "iconserver": "1494", "iconfarm": 2}, "title": {"_content": "In der S\u00fcdwestpfalz"}, "views": "1134", "comments": {"_content": "1"}, "tags": {"tag": [{"id": "126555647-28234998854-18749678", "raw": "Altschlossfelsen", "_content": "altschlossfelsen"}, {"id": "126555647-28234998854-4073146", "raw": "Sommerakademie", "_content": "sommerakademie"}, {"id": "126555647-28234998854-8668", "raw": "Struktur", "_content": "struktur"}]}, "favpersons": [{"nsid": "149392270@N02", "username": "karlheinz klingbeil", "realname": "Karlheinz Klingbeil", "favedate": "1521368321", "iconserver": "4510", "iconfarm": 5, "contact": 0, "friend": 0, "family": 0}, {"nsid": "139781001@N08", "username": "xjohnxsmith777", "realname": "John Smith", "favedate": "1518051903", "iconserver": "4757", "iconfarm": 5, "contact": 0, "friend": 0, "family": 0}, {"nsid": "82973500@N07", "username": "Mile_pile", "realname": "", "favedate": "1517990388", "iconserver": "7397", "iconfarm": 8, "contact": 0, "friend": 0, "family": 0}, {"nsid": "47134714@N04", "username": "fossiled", "realname": "Ed", "favedate": "1516917869", "iconserver": "7584", "iconfarm": 8, "contact": 0, "friend": 0, "family": 0}, {"nsid": "17853727@N00", "username": "pharoahsax", "realname": "PMBVW Pharoahsax", "favedate": "1503163492", "iconserver": "5475", "iconfarm": 6, "contact": 0, "friend": 0, "family": 0}, {"nsid": "146722593@N08", "username": "nordelch61", "realname": "", "favedate": "1484942204", "iconserver": "679", "iconfarm": 1, "contact": 0, "friend": 0, "family": 0}, {"nsid": "28991435@N02", "username": "hedbavny", "realname": "Ingrid Hedbavny", "favedate": "1483484390", "iconserver": "8550", "iconfarm": 9, "contact": 0, "friend": 0, "family": 0}, {"nsid": "100375504@N06", "username": "leonard411", "realname": "Michael Leonard", "favedate": "1479419430", "iconserver": "3916", "iconfarm": 4, "contact": 0, "friend": 0, "family": 0}, {"nsid": "143254993@N06", "username": "tanjatall", "realname": "Tatjana Olsson", "favedate": "1479398695", "iconserver": "262", "iconfarm": 1, "contact": 0, "friend": 0, "family": 0}, {"nsid": "100269862@N05", "username": "\u00a8\u00b0\u200b\u200b\u200b\u200b\u200b{N@tur'elle}\u200b\u200b\u200b\u200b\u00b0\u200b", "realname": "", "favedate": "1478260554", "iconserver": "4678", "iconfarm": 5, "contact": 0, "friend": 0, "family": 0}], "faves": 24}, "stat": "ok"}, {"photo": {"id": "36091031731", "secret": "129b1e2b11", "server": "4292", "farm": 5, "owner": {"nsid": "126576977@N07", "username": "Pfalzknipser", "realname": "", "iconserver": "1494", "iconfarm": 2}, "title": {"_content": "Heavy Metal I"}, "views": "16557", "comments": {"_content": "9"}, "tags": {"tag": [{"id": "126555647-36091031731-31348", "raw": "Luxembourg", "_content": "luxembourg"}, {"id": "126555647-36091031731-195852", "raw": "Philharmonie", "_content": "philharmonie"}, {"id": "126555647-36091031731-20100", "raw": "SW", "_content": "sw"}, {"id": "126555647-36091031731-4073146", "raw": "Sommerakademie", "_content": "sommerakademie"}]}, "favpersons": [{"nsid": "47909934@N07", "username": "MoJo0103", "realname": "", "favedate": "1521838100", "iconserver": "6061", "iconfarm": 7, "contact": 0, "friend": 0, "family": 0}, {"nsid": "141138864@N05", "username": "etsifaut", "realname": "Fran\u00e7ois ROBERT", "favedate": "1518712268", "iconserver": "4170", "iconfarm": 5, "contact": 0, "friend": 0, "family": 0}, {"nsid": "144695820@N07", "username": "Thorsten Burkard", "realname": "", "favedate": "1517852732", "iconserver": "5465", "iconfarm": 6, "contact": 0, "friend": 0, "family": 0}, {"nsid": "47134714@N04", "username": "fossiled", "realname": "Ed", "favedate": "1516917819", "iconserver": "7584", "iconfarm": 8, "contact": 0, "friend": 0, "family": 0}, {"nsid": "24910006@N02", "username": "Dierk Topp", "realname": "", "favedate": "1514823464", "iconserver": "8263", "iconfarm": 9, "contact": 0, "friend": 0, "family": 0}, {"nsid": "91492606@N07", "username": "David Rosen Photography", "realname": "David Rosen", "favedate": "1510664991", "iconserver": "5580", "iconfarm": 6, "contact": 0, "friend": 0, "family": 0}, {"nsid": "158551334@N02", "username": "Linsenkit0815", "realname": "Chris J.", "favedate": "1510616709", "iconserver": "4475", "iconfarm": 5, "contact": 0, "friend": 0, "family": 0}, {"nsid": "136797497@N08", "username": "Panasonikon", "realname": "", "favedate": "1507798645", "iconserver": "5747", "iconfarm": 6, "contact": 0, "friend": 0, "family": 0}, {"nsid": "100513133@N08", "username": "Peter Krumme", "realname": "Peter Krumme", "favedate": "1506332639", "iconserver": "7383", "iconfarm": 8, "contact": 0, "friend": 0, "family": 0}, {"nsid": "154806086@N06", "username": "Gimmeldingen_Palatinate", "realname": "Michael Gall", "favedate": "1505125485", "iconserver": "4407", "iconfarm": 5, "contact": 0, "friend": 0, "family": 0}], "faves": 222}, "stat": "ok"}, {"photo": {"id": "29760348194", "secret": "96794b72d8", "server": "8549", "farm": 9, "owner": {"nsid": "126576977@N07", "username": "Pfalzknipser", "realname": "", "iconserver": "1494", "iconfarm": 2}, "title": {"_content": "Nebel im Pf\u00e4lzerwald"}, "views": "1424", "comments": {"_content": "1"}, "tags": {"tag": [{"id": "126555647-29760348194-60623418", "raw": "Kaltenbrunnertal", "_content": "kaltenbrunnertal"}, {"id": "126555647-29760348194-40955", "raw": "Landschaft", "_content": "landschaft"}, {"id": "126555647-29760348194-3936072", "raw": "Lichtstimmung", "_content": "lichtstimmung"}, {"id": "126555647-29760348194-43931276", "raw": "Pf\u00c3\u00a4lzerwald", "_content": "pf\u00e3\u00a4lzerwald"}]}, "favpersons": [{"nsid": "11588396@N03", "username": "Tony Pulokas", "realname": "Tony Pulokas", "favedate": "1519838879", "iconserver": "8745", "iconfarm": 9, "contact": 0, "friend": 0, "family": 0}, {"nsid": "139781001@N08", "username": "xjohnxsmith777", "realname": "John Smith", "favedate": "1518051872", "iconserver": "4757", "iconfarm": 5, "contact": 0, "friend": 0, "family": 0}, {"nsid": "133849281@N06", "username": "manolohp77", "realname": "Manuel Hern\u00e1ndez", "favedate": "1503254120", "iconserver": "4725", "iconfarm": 5, "contact": 0, "friend": 0, "family": 0}, {"nsid": "96230092@N07", "username": "martine_ferron", "realname": "Martine Ferron", "favedate": "1503210767", "iconserver": "4618", "iconfarm": 5, "contact": 0, "friend": 0, "family": 0}, {"nsid": "17853727@N00", "username": "pharoahsax", "realname": "PMBVW Pharoahsax", "favedate": "1503163468", "iconserver": "5475", "iconfarm": 6, "contact": 0, "friend": 0, "family": 0}, {"nsid": "46376601@N02", "username": "gerrit-worldwide.de", "realname": "", "favedate": "1493490699", "iconserver": "2324", "iconfarm": 3, "contact": 0, "friend": 0, "family": 0}, {"nsid": "94340476@N04", "username": "MC-80", "realname": "", "favedate": "1492268928", "iconserver": "7447", "iconfarm": 8, "contact": 0, "friend": 0, "family": 0}, {"nsid": "146722593@N08", "username": "nordelch61", "realname": "", "favedate": "1488663575", "iconserver": "679", "iconfarm": 1, "contact": 0, "friend": 0, "family": 0}, {"nsid": "147298360@N04", "username": "elisabettapartini", "realname": "elisabetta partini", "favedate": "1486281247", "iconserver": "661", "iconfarm": 1, "contact": 0, "friend": 0, "family": 0}, {"nsid": "55975101@N06", "username": "Desiree van Oeffelt", "realname": "", "favedate": "1485518590", "iconserver": "1265", "iconfarm": 2, "contact": 0, "friend": 0, "family": 0}], "faves": 47}, "stat": "ok"}, {"photo": {"id": "30890698692", "secret": "48d6228fdb", "server": "5751", "farm": 6, "owner": {"nsid": "126576977@N07", "username": "Pfalzknipser", "realname": "", "iconserver": "1494", "iconfarm": 2}, "title": {"_content": "Im Wasgau"}, "views": "20996", "comments": {"_content": "55"}, "tags": {"tag": [{"id": "126555647-30890698692-40955", "raw": "Landschaft", "_content": "landschaft"}, {"id": "126555647-30890698692-3936072", "raw": "Lichtstimmung", "_content": "lichtstimmung"}, {"id": "126555647-30890698692-3839", "raw": "Nebel", "_content": "nebel"}]}, "favpersons": [{"nsid": "133692007@N02", "username": "lidschlag60", "realname": "", "favedate": "1518561676", "iconserver": "485", "iconfarm": 1, "contact": 0, "friend": 0, "family": 0}, {"nsid": "55047949@N06", "username": "P_A_S_M", "realname": "Pascal M\u00fcller", "favedate": "1518025273", "iconserver": "1680", "iconfarm": 2, "contact": 0, "friend": 0, "family": 0}, {"nsid": "158882818@N06", "username": "Sugar Beet Pete", "realname": "Peter Beesley", "favedate": "1518010445", "iconserver": "4505", "iconfarm": 5, "contact": 0, "friend": 0, "family": 0}, {"nsid": "135953877@N02", "username": "mtippett77", "realname": "Mark Tippett", "favedate": "1509217915", "iconserver": "1594", "iconfarm": 2, "contact": 0, "friend": 0, "family": 0}, {"nsid": "138030024@N05", "username": "Niko Benas", "realname": "Niko  Benas", "favedate": "1508247727", "iconserver": "1565", "iconfarm": 2, "contact": 0, "friend": 0, "family": 0}, {"nsid": "61208756@N03", "username": "Stijn Smits", "realname": "", "favedate": "1506660392", "iconserver": "7296", "iconfarm": 8, "contact": 0, "friend": 0, "family": 0}, {"nsid": "101862560@N03", "username": "UpuautX", "realname": "Simon Forte", "favedate": "1504848159", "iconserver": "438", "iconfarm": 1, "contact": 0, "friend": 0, "family": 0}, {"nsid": "151156570@N04", "username": "saajlas", "realname": "Sasha Pekaz", "favedate": "1503211026", "iconserver": "4300", "iconfarm": 5, "contact": 0, "friend": 0, "family": 0}, {"nsid": "96230092@N07", "username": "martine_ferron", "realname": "Martine Ferron", "favedate": "1503210754", "iconserver": "4618", "iconfarm": 5, "contact": 0, "friend": 0, "family": 0}, {"nsid": "146541830@N04", "username": "Hans Hameldinger", "realname": "Hans Hameldinger", "favedate": "1501756900", "iconserver": "642", "iconfarm": 1, "contact": 0, "friend": 0, "family": 0}], "faves": 1002}, "stat": "ok"}, {"photo": {"id": "31404044576", "secret": "5f4270e683", "server": "5509", "farm": 6, "owner": {"nsid": "126576977@N07", "username": "Pfalzknipser", "realname": "", "iconserver": "1494", "iconfarm": 2}, "title": {"_content": "Herbstwinter"}, "views": "1431", "comments": {"_content": "1"}, "tags": {"tag": [{"id": "126555647-31404044576-44305", "raw": "B\u00e4ume", "_content": "b\u00e4ume"}, {"id": "126555647-31404044576-921200", "raw": "Herbstfarben", "_content": "herbstfarben"}, {"id": "126555647-31404044576-3936072", "raw": "Lichtstimmung", "_content": "lichtstimmung"}, {"id": "126555647-31404044576-3839", "raw": "Nebel", "_content": "nebel"}]}, "favpersons": [{"nsid": "28040142@N07", "username": "craig.denford", "realname": "Craig Denford", "favedate": "1522186408", "iconserver": "5699", "iconfarm": 6, "contact": 0, "friend": 0, "family": 0}, {"nsid": "126536619@N04", "username": "monika_swadowska", "realname": "Monika Swadowska", "favedate": "1521369787", "iconserver": "3871", "iconfarm": 4, "contact": 0, "friend": 0, "family": 0}, {"nsid": "155571901@N07", "username": "patrickroedel", "realname": "Patrick R\u00f6del", "favedate": "1518023270", "iconserver": "0", "iconfarm": 0, "contact": 0, "friend": 0, "family": 0}, {"nsid": "70803297@N00", "username": "woodswalk", "realname": "", "favedate": "1518015420", "iconserver": "5560", "iconfarm": 6, "contact": 0, "friend": 0, "family": 0}, {"nsid": "129853901@N06", "username": "Hubert VIGNAUX instinct nature", "realname": "", "favedate": "1515868303", "iconserver": "8680", "iconfarm": 9, "contact": 0, "friend": 0, "family": 0}, {"nsid": "158551334@N02", "username": "Linsenkit0815", "realname": "Chris J.", "favedate": "1510616791", "iconserver": "4475", "iconfarm": 5, "contact": 0, "friend": 0, "family": 0}, {"nsid": "92021641@N06", "username": "Powderpuff GP", "realname": "", "favedate": "1501373562", "iconserver": "8092", "iconfarm": 9, "contact": 0, "friend": 0, "family": 0}, {"nsid": "94340476@N04", "username": "MC-80", "realname": "", "favedate": "1492268849", "iconserver": "7447", "iconfarm": 8, "contact": 0, "friend": 0, "family": 0}, {"nsid": "118877287@N03", "username": "ArtundUnart", "realname": "ArtundUnart", "favedate": "1491897336", "iconserver": "523", "iconfarm": 1, "contact": 0, "friend": 0, "family": 0}, {"nsid": "120099037@N06", "username": "sdc_foto", "realname": "Reimund Schmidt-De Caluwe", "favedate": "1490003287", "iconserver": "3599", "iconfarm": 4, "contact": 0, "friend": 0, "family": 0}], "faves": 42}, "stat": "ok"}, {"photo": {"id": "27542090375", "secret": "7bf0c294dc", "server": "7423", "farm": 8, "owner": {"nsid": "126576977@N07", "username": "Pfalzknipser", "realname": "", "iconserver": "1494", "iconfarm": 2}, "title": {"_content": "Vorderpfalz"}, "views": "1123", "comments": {"_content": "1"}, "tags": {"tag": [{"id": "126555647-27542090375-8585", "raw": "Blumen", "_content": "blumen"}, {"id": "126555647-27542090375-40955", "raw": "Landschaft", "_content": "landschaft"}, {"id": "126555647-27542090375-3936072", "raw": "Lichtstimmung", "_content": "lichtstimmung"}, {"id": "126555647-27542090375-128325319", "raw": "Mittelhardt", "_content": "mittelhardt"}, {"id": "126555647-27542090375-265356", "raw": "Mohn", "_content": "mohn"}]}, "favpersons": [{"nsid": "60571553@N07", "username": "sascha-laessig-fotografie.de", "realname": "Sascha L\u00e4ssig", "favedate": "1484642817", "iconserver": "3900", "iconfarm": 4, "contact": 0, "friend": 0, "family": 0}, {"nsid": "96307955@N00", "username": "Totallyme (still very busy with workload...)", "realname": "Gunta", "favedate": "1479411482", "iconserver": "5794", "iconfarm": 6, "contact": 0, "friend": 0, "family": 0}, {"nsid": "143254993@N06", "username": "tanjatall", "realname": "Tatjana Olsson", "favedate": "1479398913", "iconserver": "262", "iconfarm": 1, "contact": 0, "friend": 0, "family": 0}, {"nsid": "137124182@N08", "username": "Fannie Jowski Photography", "realname": "", "favedate": "1479392947", "iconserver": "1467", "iconfarm": 2, "contact": 0, "friend": 0, "family": 0}, {"nsid": "43545274@N05", "username": "**Monkey**", "realname": "", "favedate": "1479355898", "iconserver": "3878", "iconfarm": 4, "contact": 0, "friend": 0, "family": 0}, {"nsid": "116004225@N05", "username": "annigabud", "realname": "Anni Gabud", "favedate": "1478298121", "iconserver": "2855", "iconfarm": 3, "contact": 0, "friend": 0, "family": 0}, {"nsid": "131128793@N03", "username": "luca_bacchella", "realname": "Luca Bacchella", "favedate": "1478241599", "iconserver": "1706", "iconfarm": 2, "contact": 0, "friend": 0, "family": 0}, {"nsid": "139435350@N02", "username": "D.Sinkute", "realname": "D.Sinkute Photography", "favedate": "1476255603", "iconserver": "4401", "iconfarm": 5, "contact": 0, "friend": 0, "family": 0}, {"nsid": "138813775@N07", "username": "frankpieritz", "realname": "Frank Pieritz", "favedate": "1476127514", "iconserver": "4421", "iconfarm": 5, "contact": 0, "friend": 0, "family": 0}, {"nsid": "94340476@N04", "username": "MC-80", "realname": "", "favedate": "1475002837", "iconserver": "7447", "iconfarm": 8, "contact": 0, "friend": 0, "family": 0}], "faves": 25}, "stat": "ok"}, {"photo": {"id": "30120119003", "secret": "4f99b040b5", "server": "5590", "farm": 6, "owner": {"nsid": "126576977@N07", "username": "Pfalzknipser", "realname": "", "iconserver": "1494", "iconfarm": 2}, "title": {"_content": "Blick von Burg Lindelbrunn"}, "views": "1334", "comments": {"_content": "1"}, "tags": {"tag": [{"id": "126555647-30120119003-921200", "raw": "Herbstfarben", "_content": "herbstfarben"}, {"id": "126555647-30120119003-3936072", "raw": "Lichtstimmung", "_content": "lichtstimmung"}, {"id": "126555647-30120119003-207600", "raw": "Lindelbrunn", "_content": "lindelbrunn"}, {"id": "126555647-30120119003-3839", "raw": "Nebel", "_content": "nebel"}]}, "favpersons": [{"nsid": "34805145@N04", "username": "chris_montreal", "realname": "Chris", "favedate": "1514905286", "iconserver": "3309", "iconfarm": 4, "contact": 0, "friend": 0, "family": 0}, {"nsid": "96230092@N07", "username": "martine_ferron", "realname": "Martine Ferron", "favedate": "1503210762", "iconserver": "4618", "iconfarm": 5, "contact": 0, "friend": 0, "family": 0}, {"nsid": "142658312@N02", "username": "angelika.kart", "realname": "Angelika Kart", "favedate": "1499536700", "iconserver": "4478", "iconfarm": 5, "contact": 0, "friend": 0, "family": 0}, {"nsid": "130630754@N05", "username": "siimvaar", "realname": "Siim Vaar", "favedate": "1481134845", "iconserver": "7652", "iconfarm": 8, "contact": 0, "friend": 0, "family": 0}, {"nsid": "34188518@N04", "username": "whitelily20099", "realname": "", "favedate": "1479833102", "iconserver": "0", "iconfarm": 0, "contact": 0, "friend": 0, "family": 0}, {"nsid": "112196494@N02", "username": "thunderbird-72", "realname": "", "favedate": "1479415461", "iconserver": "3860", "iconfarm": 4, "contact": 0, "friend": 0, "family": 0}, {"nsid": "143254993@N06", "username": "tanjatall", "realname": "Tatjana Olsson", "favedate": "1479398670", "iconserver": "262", "iconfarm": 1, "contact": 0, "friend": 0, "family": 0}, {"nsid": "137124182@N08", "username": "Fannie Jowski Photography", "realname": "", "favedate": "1479392927", "iconserver": "1467", "iconfarm": 2, "contact": 0, "friend": 0, "family": 0}, {"nsid": "126692978@N02", "username": "B\u00f2 L\u1ea1c", "realname": "Ch\u00ec  G\u1ed7", "favedate": "1479367815", "iconserver": "4329", "iconfarm": 5, "contact": 0, "friend": 0, "family": 0}, {"nsid": "43545274@N05", "username": "**Monkey**", "realname": "", "favedate": "1479355834", "iconserver": "3878", "iconfarm": 4, "contact": 0, "friend": 0, "family": 0}], "faves": 26}, "stat": "ok"}, {"photo": {"id": "30304661061", "secret": "be36f4fdc6", "server": "5600", "farm": 6, "owner": {"nsid": "126576977@N07", "username": "Pfalzknipser", "realname": "", "iconserver": "1494", "iconfarm": 2}, "title": {"_content": "Nebel im Pf\u00e4lzerwald"}, "views": "8685", "comments": {"_content": "22"}, "tags": {"tag": [{"id": "126555647-30304661061-25299152", "raw": "B\u00c3\u00a4ume", "_content": "b\u00e3\u00a4ume"}, {"id": "126555647-30304661061-3936072", "raw": "Lichtstimmung", "_content": "lichtstimmung"}, {"id": "126555647-30304661061-43931276", "raw": "Pf\u00c3\u00a4lzerwald", "_content": "pf\u00e3\u00a4lzerwald"}]}, "favpersons": [{"nsid": "143533968@N06", "username": "lorenzomazzetti", "realname": "lorenzo mazzetti", "favedate": "1520374063", "iconserver": "7479", "iconfarm": 8, "contact": 0, "friend": 0, "family": 0}, {"nsid": "139781001@N08", "username": "xjohnxsmith777", "realname": "John Smith", "favedate": "1518051864", "iconserver": "4757", "iconfarm": 5, "contact": 0, "friend": 0, "family": 0}, {"nsid": "155571901@N07", "username": "patrickroedel", "realname": "Patrick R\u00f6del", "favedate": "1518023299", "iconserver": "0", "iconfarm": 0, "contact": 0, "friend": 0, "family": 0}, {"nsid": "36274845@N05", "username": "\u00b7 NORDAN \u00b7", "realname": "\u00c1lvaro Framis y Sarr\u00eda", "favedate": "1504430353", "iconserver": "7761", "iconfarm": 8, "contact": 0, "friend": 0, "family": 0}, {"nsid": "96230092@N07", "username": "martine_ferron", "realname": "Martine Ferron", "favedate": "1503210764", "iconserver": "4618", "iconfarm": 5, "contact": 0, "friend": 0, "family": 0}, {"nsid": "17853727@N00", "username": "pharoahsax", "realname": "PMBVW Pharoahsax", "favedate": "1503163465", "iconserver": "5475", "iconfarm": 6, "contact": 0, "friend": 0, "family": 0}, {"nsid": "146228859@N08", "username": "R0bertas", "realname": "", "favedate": "1501350856", "iconserver": "4303", "iconfarm": 5, "contact": 0, "friend": 0, "family": 0}, {"nsid": "142658312@N02", "username": "angelika.kart", "realname": "Angelika Kart", "favedate": "1499536699", "iconserver": "4478", "iconfarm": 5, "contact": 0, "friend": 0, "family": 0}, {"nsid": "35451911@N06", "username": "trobel", "realname": "", "favedate": "1497036382", "iconserver": "0", "iconfarm": 0, "contact": 0, "friend": 0, "family": 0}, {"nsid": "94340476@N04", "username": "MC-80", "realname": "", "favedate": "1492268924", "iconserver": "7447", "iconfarm": 8, "contact": 0, "friend": 0, "family": 0}], "faves": 408}, "stat": "ok"}, {"photo": {"id": "31215161764", "secret": "52d53b2df7", "server": "295", "farm": 1, "owner": {"nsid": "126576977@N07", "username": "Pfalzknipser", "realname": "", "iconserver": "1494", "iconfarm": 2}, "title": {"_content": "Raureif"}, "views": "7744", "comments": {"_content": "9"}, "tags": {"tag": [{"id": "126555647-31215161764-44305", "raw": "B\u00e4ume", "_content": "b\u00e4ume"}, {"id": "126555647-31215161764-67467", "raw": "Raureif", "_content": "raureif"}, {"id": "126555647-31215161764-8668", "raw": "Struktur", "_content": "struktur"}, {"id": "126555647-31215161764-201", "raw": "Winter", "_content": "winter"}]}, "favpersons": [{"nsid": "70803297@N00", "username": "woodswalk", "realname": "", "favedate": "1518015601", "iconserver": "5560", "iconfarm": 6, "contact": 0, "friend": 0, "family": 0}, {"nsid": "93185434@N08", "username": "All Shine", "realname": "", "favedate": "1517994143", "iconserver": "8111", "iconfarm": 9, "contact": 0, "friend": 0, "family": 0}, {"nsid": "47134714@N04", "username": "fossiled", "realname": "Ed", "favedate": "1516917840", "iconserver": "7584", "iconfarm": 8, "contact": 0, "friend": 0, "family": 0}, {"nsid": "98282428@N07", "username": "Steinkreisphoto", "realname": "J\u00fcrgen L\u00fcno", "favedate": "1512722328", "iconserver": "0", "iconfarm": 0, "contact": 0, "friend": 0, "family": 0}, {"nsid": "77144886@N08", "username": "FujiFritz", "realname": "", "favedate": "1511713927", "iconserver": "7311", "iconfarm": 8, "contact": 0, "friend": 0, "family": 0}, {"nsid": "158551334@N02", "username": "Linsenkit0815", "realname": "Chris J.", "favedate": "1510616768", "iconserver": "4475", "iconfarm": 5, "contact": 0, "friend": 0, "family": 0}, {"nsid": "125148179@N02", "username": "Holger Losekann", "realname": "Holger Losekann", "favedate": "1493919967", "iconserver": "8578", "iconfarm": 9, "contact": 0, "friend": 0, "family": 0}, {"nsid": "66517913@N05", "username": "Matt C68", "realname": "Matthew Cackett", "favedate": "1489964930", "iconserver": "4258", "iconfarm": 5, "contact": 0, "friend": 0, "family": 0}, {"nsid": "142554984@N03", "username": "drop_m", "realname": "Mattia Ferraboli", "favedate": "1487845539", "iconserver": "491", "iconfarm": 1, "contact": 0, "friend": 0, "family": 0}, {"nsid": "98121102@N03", "username": "aravena64", "realname": "Carlos Aravena", "favedate": "1487826322", "iconserver": "4513", "iconfarm": 5, "contact": 0, "friend": 0, "family": 0}], "faves": 223}, "stat": "ok"}, {"photo": {"id": "35971591273", "secret": "3672872a01", "server": "4354", "farm": 5, "owner": {"nsid": "126576977@N07", "username": "Pfalzknipser", "realname": "", "iconserver": "1494", "iconfarm": 2}, "title": {"_content": "Mehlinger Heide"}, "views": "1132", "comments": {"_content": "7"}, "tags": {"tag": [{"id": "126555647-35971591273-94288", "raw": "Heide", "_content": "heide"}, {"id": "126555647-35971591273-40955", "raw": "Landschaft", "_content": "landschaft"}, {"id": "126555647-35971591273-3936072", "raw": "Lichtstimmung", "_content": "lichtstimmung"}, {"id": "126555647-35971591273-5057816", "raw": "Mehlingen", "_content": "mehlingen"}, {"id": "126555647-35971591273-3839", "raw": "Nebel", "_content": "nebel"}]}, "favpersons": [{"nsid": "47909934@N07", "username": "MoJo0103", "realname": "", "favedate": "1521838091", "iconserver": "6061", "iconfarm": 7, "contact": 0, "friend": 0, "family": 0}, {"nsid": "133823924@N05", "username": "valade99", "realname": "Dominique DUPUYDENUS", "favedate": "1518041361", "iconserver": "5660", "iconfarm": 6, "contact": 0, "friend": 0, "family": 0}, {"nsid": "120594978@N03", "username": "\u0651 \u2224\u20a1o\u2113d Meat Industry\u2224", "realname": "Roberto", "favedate": "1517340021", "iconserver": "739", "iconfarm": 1, "contact": 0, "friend": 0, "family": 0}, {"nsid": "87478051@N04", "username": "bartomac", "realname": "", "favedate": "1516492122", "iconserver": "323", "iconfarm": 1, "contact": 0, "friend": 0, "family": 0}, {"nsid": "152123221@N07", "username": "ANVOTO", "realname": "", "favedate": "1515691594", "iconserver": "4370", "iconfarm": 5, "contact": 0, "friend": 0, "family": 0}, {"nsid": "132127013@N04", "username": "heinzg1967", "realname": "Gerd Heinz", "favedate": "1514913215", "iconserver": "391", "iconfarm": 1, "contact": 0, "friend": 0, "family": 0}, {"nsid": "97554600@N04", "username": "Philipp Zieger - www.philippzieger-photographie.de", "realname": "Philipp Zieger", "favedate": "1512717822", "iconserver": "7287", "iconfarm": 8, "contact": 0, "friend": 0, "family": 0}, {"nsid": "148402203@N02", "username": "Roi.C", "realname": "Roi.C .", "favedate": "1506793864", "iconserver": "5635", "iconfarm": 6, "contact": 0, "friend": 0, "family": 0}, {"nsid": "100513133@N08", "username": "Peter Krumme", "realname": "Peter Krumme", "favedate": "1506332628", "iconserver": "7383", "iconfarm": 8, "contact": 0, "friend": 0, "family": 0}, {"nsid": "94340476@N04", "username": "MC-80", "realname": "", "favedate": "1504888496", "iconserver": "7447", "iconfarm": 8, "contact": 0, "friend": 0, "family": 0}], "faves": 43}, "stat": "ok"}, {"photo": {"id": "31451732300", "secret": "4b836ddd59", "server": "479", "farm": 1, "owner": {"nsid": "126576977@N07", "username": "Pfalzknipser", "realname": "", "iconserver": "1494", "iconfarm": 2}, "title": {"_content": "Sonne und Nebel"}, "views": "9527", "comments": {"_content": "13"}, "tags": {"tag": [{"id": "126555647-31451732300-921200", "raw": "Herbstfarben", "_content": "herbstfarben"}, {"id": "126555647-31451732300-3936072", "raw": "Lichtstimmung", "_content": "lichtstimmung"}, {"id": "126555647-31451732300-41600", "raw": "Wald", "_content": "wald"}]}, "favpersons": [{"nsid": "28040142@N07", "username": "craig.denford", "realname": "Craig Denford", "favedate": "1522186388", "iconserver": "5699", "iconfarm": 6, "contact": 0, "friend": 0, "family": 0}, {"nsid": "149943419@N03", "username": "EJ Kipp", "realname": "", "favedate": "1521421160", "iconserver": "4458", "iconfarm": 5, "contact": 0, "friend": 0, "family": 0}, {"nsid": "107905622@N04", "username": "christensenbruce320", "realname": "Bruce Christensen", "favedate": "1519942772", "iconserver": "2882", "iconfarm": 3, "contact": 0, "friend": 0, "family": 0}, {"nsid": "47134714@N04", "username": "fossiled", "realname": "Ed", "favedate": "1516917843", "iconserver": "7584", "iconfarm": 8, "contact": 0, "friend": 0, "family": 0}, {"nsid": "158685114@N05", "username": "S. Kemkes", "realname": "Sabrina Kemkes", "favedate": "1516016757", "iconserver": "4660", "iconfarm": 5, "contact": 0, "friend": 0, "family": 0}, {"nsid": "129853901@N06", "username": "Hubert VIGNAUX instinct nature", "realname": "", "favedate": "1515868298", "iconserver": "8680", "iconfarm": 9, "contact": 0, "friend": 0, "family": 0}, {"nsid": "58625834@N06", "username": "Peter Dobner", "realname": "Peter Dobner", "favedate": "1515101622", "iconserver": "4202", "iconfarm": 5, "contact": 0, "friend": 0, "family": 0}, {"nsid": "90552259@N03", "username": "rael11ld", "realname": "", "favedate": "1515089097", "iconserver": "3740", "iconfarm": 4, "contact": 0, "friend": 0, "family": 0}, {"nsid": "12149353@N03", "username": "Francis. R", "realname": "", "favedate": "1514937055", "iconserver": "7316", "iconfarm": 8, "contact": 0, "friend": 0, "family": 0}, {"nsid": "158551334@N02", "username": "Linsenkit0815", "realname": "Chris J.", "favedate": "1510616786", "iconserver": "4475", "iconfarm": 5, "contact": 0, "friend": 0, "family": 0}], "faves": 287}, "stat": "ok"}, {"photo": {"id": "30755736275", "secret": "59247c604f", "server": "5762", "farm": 6, "owner": {"nsid": "126576977@N07", "username": "Pfalzknipser", "realname": "", "iconserver": "1494", "iconfarm": 2}, "title": {"_content": "Blick von Burg Lindelbrunn"}, "views": "14438", "comments": {"_content": "13"}, "tags": {"tag": [{"id": "126555647-30755736275-40955", "raw": "Landschaft", "_content": "landschaft"}, {"id": "126555647-30755736275-3936072", "raw": "Lichtstimmung", "_content": "lichtstimmung"}, {"id": "126555647-30755736275-207600", "raw": "Lindelbrunn", "_content": "lindelbrunn"}, {"id": "126555647-30755736275-3839", "raw": "Nebel", "_content": "nebel"}]}, "favpersons": [{"nsid": "66619908@N02", "username": "michael.han", "realname": "", "favedate": "1521350171", "iconserver": "7443", "iconfarm": 8, "contact": 0, "friend": 0, "family": 0}, {"nsid": "139781001@N08", "username": "xjohnxsmith777", "realname": "John Smith", "favedate": "1518051860", "iconserver": "4757", "iconfarm": 5, "contact": 0, "friend": 0, "family": 0}, {"nsid": "155571901@N07", "username": "patrickroedel", "realname": "Patrick R\u00f6del", "favedate": "1518023288", "iconserver": "0", "iconfarm": 0, "contact": 0, "friend": 0, "family": 0}, {"nsid": "144701591@N02", "username": "Katrins Picture Time", "realname": "", "favedate": "1509111652", "iconserver": "5704", "iconfarm": 6, "contact": 0, "friend": 0, "family": 0}, {"nsid": "115834510@N03", "username": "skk85230", "realname": "JEN-CHUAN TSAI", "favedate": "1504933931", "iconserver": "4679", "iconfarm": 5, "contact": 0, "friend": 0, "family": 0}, {"nsid": "17853727@N00", "username": "pharoahsax", "realname": "PMBVW Pharoahsax", "favedate": "1503163461", "iconserver": "5475", "iconfarm": 6, "contact": 0, "friend": 0, "family": 0}, {"nsid": "124865995@N03", "username": "kaefer63", "realname": "Richard", "favedate": "1483477278", "iconserver": "5803", "iconfarm": 6, "contact": 0, "friend": 0, "family": 0}, {"nsid": "12316852@N06", "username": "Aesum", "realname": "Angelo Domini", "favedate": "1481497213", "iconserver": "4336", "iconfarm": 5, "contact": 0, "friend": 0, "family": 0}, {"nsid": "127226743@N02", "username": "Dimitris Graffin", "realname": "Dimitris Kamaras", "favedate": "1481458414", "iconserver": "5591", "iconfarm": 6, "contact": 0, "friend": 0, "family": 0}, {"nsid": "130630754@N05", "username": "siimvaar", "realname": "Siim Vaar", "favedate": "1481134845", "iconserver": "7652", "iconfarm": 8, "contact": 0, "friend": 0, "family": 0}], "faves": 335}, "stat": "ok"}, {"photo": {"id": "31320978616", "secret": "1acf5be8e2", "server": "5786", "farm": 6, "owner": {"nsid": "126576977@N07", "username": "Pfalzknipser", "realname": "", "iconserver": "1494", "iconfarm": 2}, "title": {"_content": "Nebel im Pf\u00e4lzerwald"}, "views": "1573", "comments": {"_content": "4"}, "tags": {"tag": [{"id": "126555647-31320978616-44305", "raw": "B\u00e4ume", "_content": "b\u00e4ume"}, {"id": "126555647-31320978616-921200", "raw": "Herbstfarben", "_content": "herbstfarben"}, {"id": "126555647-31320978616-60623418", "raw": "Kaltenbrunnertal", "_content": "kaltenbrunnertal"}, {"id": "126555647-31320978616-3839", "raw": "Nebel", "_content": "nebel"}]}, "favpersons": [{"nsid": "28040142@N07", "username": "craig.denford", "realname": "Craig Denford", "favedate": "1522186433", "iconserver": "5699", "iconfarm": 6, "contact": 0, "friend": 0, "family": 0}, {"nsid": "47909934@N07", "username": "MoJo0103", "realname": "", "favedate": "1521838137", "iconserver": "6061", "iconfarm": 7, "contact": 0, "friend": 0, "family": 0}, {"nsid": "136785055@N02", "username": "dominique 15", "realname": "Dominique ROUBENNE", "favedate": "1520377010", "iconserver": "5672", "iconfarm": 6, "contact": 0, "friend": 0, "family": 0}, {"nsid": "126608955@N07", "username": "Vicky Vance", "realname": "Vicky Vance", "favedate": "1514914235", "iconserver": "4663", "iconfarm": 5, "contact": 0, "friend": 0, "family": 0}, {"nsid": "146361452@N07", "username": "joern_ribu", "realname": "J\u00f6rn Ritterbusch", "favedate": "1510835898", "iconserver": "587", "iconfarm": 1, "contact": 0, "friend": 0, "family": 0}, {"nsid": "133954173@N03", "username": "Nadine Le Goff", "realname": "Nadine Le Goff", "favedate": "1510211323", "iconserver": "621", "iconfarm": 1, "contact": 0, "friend": 0, "family": 0}, {"nsid": "49779370@N06", "username": "merebara", "realname": "Igor Galarza Insausti", "favedate": "1510090810", "iconserver": "593", "iconfarm": 1, "contact": 0, "friend": 0, "family": 0}, {"nsid": "90444502@N07", "username": "robert.french57 French Images", "realname": "", "favedate": "1508056658", "iconserver": "5700", "iconfarm": 6, "contact": 0, "friend": 0, "family": 0}, {"nsid": "129560720@N06", "username": "ameyer121", "realname": "Anne Meyer", "favedate": "1503349768", "iconserver": "8567", "iconfarm": 9, "contact": 0, "friend": 0, "family": 0}, {"nsid": "151156570@N04", "username": "saajlas", "realname": "Sasha Pekaz", "favedate": "1503211020", "iconserver": "4300", "iconfarm": 5, "contact": 0, "friend": 0, "family": 0}], "faves": 67}, "stat": "ok"}, {"photo": {"id": "31685549106", "secret": "58791f3b13", "server": "584", "farm": 1, "owner": {"nsid": "126576977@N07", "username": "Pfalzknipser", "realname": "", "iconserver": "1494", "iconfarm": 2}, "title": {"_content": "Baum im Licht der untergehenden Sonne"}, "views": "1281", "comments": {"_content": "3"}, "tags": {"tag": [{"id": "126555647-31685549106-6430249", "raw": "G\u00e4u", "_content": "g\u00e4u"}, {"id": "126555647-31685549106-40955", "raw": "Landschaft", "_content": "landschaft"}, {"id": "126555647-31685549106-3936072", "raw": "Lichtstimmung", "_content": "lichtstimmung"}, {"id": "126555647-31685549106-128325319", "raw": "Mittelhardt", "_content": "mittelhardt"}]}, "favpersons": [{"nsid": "138445370@N08", "username": "claudiozangrandi", "realname": "Claudio Zangrandi", "favedate": "1520327874", "iconserver": "4695", "iconfarm": 5, "contact": 0, "friend": 0, "family": 0}, {"nsid": "36274845@N05", "username": "\u00b7 NORDAN \u00b7", "realname": "\u00c1lvaro Framis y Sarr\u00eda", "favedate": "1518358035", "iconserver": "7761", "iconfarm": 8, "contact": 0, "friend": 0, "family": 0}, {"nsid": "138030024@N05", "username": "Niko Benas", "realname": "Niko  Benas", "favedate": "1508247684", "iconserver": "1565", "iconfarm": 2, "contact": 0, "friend": 0, "family": 0}, {"nsid": "101862560@N03", "username": "UpuautX", "realname": "Simon Forte", "favedate": "1504848152", "iconserver": "438", "iconfarm": 1, "contact": 0, "friend": 0, "family": 0}, {"nsid": "114213318@N08", "username": "Gifty O'Hara", "realname": "", "favedate": "1504464065", "iconserver": "3904", "iconfarm": 4, "contact": 0, "friend": 0, "family": 0}, {"nsid": "121191063@N07", "username": "Fred Theaker", "realname": "Fred Theaker", "favedate": "1503522386", "iconserver": "816", "iconfarm": 1, "contact": 0, "friend": 0, "family": 0}, {"nsid": "17853727@N00", "username": "pharoahsax", "realname": "PMBVW Pharoahsax", "favedate": "1503163438", "iconserver": "5475", "iconfarm": 6, "contact": 0, "friend": 0, "family": 0}, {"nsid": "92021641@N06", "username": "Powderpuff GP", "realname": "", "favedate": "1501373556", "iconserver": "8092", "iconfarm": 9, "contact": 0, "friend": 0, "family": 0}, {"nsid": "142658312@N02", "username": "angelika.kart", "realname": "Angelika Kart", "favedate": "1499536689", "iconserver": "4478", "iconfarm": 5, "contact": 0, "friend": 0, "family": 0}, {"nsid": "125148179@N02", "username": "Holger Losekann", "realname": "Holger Losekann", "favedate": "1493919971", "iconserver": "8578", "iconfarm": 9, "contact": 0, "friend": 0, "family": 0}], "faves": 45}, "stat": "ok"}, {"photo": {"id": "31033191965", "secret": "7fb6352076", "server": "5510", "farm": 6, "owner": {"nsid": "126576977@N07", "username": "Pfalzknipser", "realname": "", "iconserver": "1494", "iconfarm": 2}, "title": {"_content": "Im Wasgau"}, "views": "7791", "comments": {"_content": "23"}, "tags": {"tag": [{"id": "126555647-31033191965-40955", "raw": "Landschaft", "_content": "landschaft"}, {"id": "126555647-31033191965-3936072", "raw": "Lichtstimmung", "_content": "lichtstimmung"}, {"id": "126555647-31033191965-207600", "raw": "Lindelbrunn", "_content": "lindelbrunn"}, {"id": "126555647-31033191965-3839", "raw": "Nebel", "_content": "nebel"}]}, "favpersons": [{"nsid": "152467606@N07", "username": "birgitmischewski", "realname": "Birgit Mischewski", "favedate": "1521388711", "iconserver": "4495", "iconfarm": 5, "contact": 0, "friend": 0, "family": 0}, {"nsid": "155571901@N07", "username": "patrickroedel", "realname": "Patrick R\u00f6del", "favedate": "1518023277", "iconserver": "0", "iconfarm": 0, "contact": 0, "friend": 0, "family": 0}, {"nsid": "47134714@N04", "username": "fossiled", "realname": "Ed", "favedate": "1516917852", "iconserver": "7584", "iconfarm": 8, "contact": 0, "friend": 0, "family": 0}, {"nsid": "139182941@N08", "username": "Jensens PhotoGraphy", "realname": "JensenPhotoGraphy", "favedate": "1514917846", "iconserver": "4594", "iconfarm": 5, "contact": 0, "friend": 0, "family": 0}, {"nsid": "34805145@N04", "username": "chris_montreal", "realname": "Chris", "favedate": "1514905255", "iconserver": "3309", "iconfarm": 4, "contact": 0, "friend": 0, "family": 0}, {"nsid": "133849281@N06", "username": "manolohp77", "realname": "Manuel Hern\u00e1ndez", "favedate": "1503254113", "iconserver": "4725", "iconfarm": 5, "contact": 0, "friend": 0, "family": 0}, {"nsid": "17853727@N00", "username": "pharoahsax", "realname": "PMBVW Pharoahsax", "favedate": "1503163446", "iconserver": "5475", "iconfarm": 6, "contact": 0, "friend": 0, "family": 0}, {"nsid": "93882080@N03", "username": "..::|[ retr0 '74 ]|::..", "realname": "", "favedate": "1501312543", "iconserver": "4781", "iconfarm": 5, "contact": 0, "friend": 0, "family": 0}, {"nsid": "142658312@N02", "username": "angelika.kart", "realname": "Angelika Kart", "favedate": "1499536703", "iconserver": "4478", "iconfarm": 5, "contact": 0, "friend": 0, "family": 0}, {"nsid": "125148179@N02", "username": "Holger Losekann", "realname": "Holger Losekann", "favedate": "1493919980", "iconserver": "8578", "iconfarm": 9, "contact": 0, "friend": 0, "family": 0}], "faves": 416}, "stat": "ok"}, {"photo": {"id": "26445732483", "secret": "0e2e0f4ce3", "server": "7062", "farm": 8, "owner": {"nsid": "126576977@N07", "username": "Pfalzknipser", "realname": "", "iconserver": "1494", "iconfarm": 2}, "title": {"_content": "Nasses Gras"}, "views": "5229", "comments": {"_content": "11"}, "tags": {"tag": [{"id": "126555647-26445732483-21830", "raw": "Gras", "_content": "gras"}, {"id": "126555647-26445732483-20100", "raw": "SW", "_content": "sw"}, {"id": "126555647-26445732483-8668", "raw": "Struktur", "_content": "struktur"}]}, "favpersons": [{"nsid": "70803297@N00", "username": "woodswalk", "realname": "", "favedate": "1518015675", "iconserver": "5560", "iconfarm": 6, "contact": 0, "friend": 0, "family": 0}, {"nsid": "12149353@N03", "username": "Francis. R", "realname": "", "favedate": "1514937083", "iconserver": "7316", "iconfarm": 8, "contact": 0, "friend": 0, "family": 0}, {"nsid": "113344254@N02", "username": "Cybister1968", "realname": "Michael W. Hilgert", "favedate": "1514578832", "iconserver": "5511", "iconfarm": 6, "contact": 0, "friend": 0, "family": 0}, {"nsid": "134285130@N04", "username": "mikhailprudka", "realname": "Mikhail Prudka", "favedate": "1489334192", "iconserver": "3956", "iconfarm": 4, "contact": 0, "friend": 0, "family": 0}, {"nsid": "143254993@N06", "username": "tanjatall", "realname": "Tatjana Olsson", "favedate": "1479399155", "iconserver": "262", "iconfarm": 1, "contact": 0, "friend": 0, "family": 0}, {"nsid": "66881686@N08", "username": "Toufik Medjahed", "realname": "The Algerian", "favedate": "1478297839", "iconserver": "5594", "iconfarm": 6, "contact": 0, "friend": 0, "family": 0}, {"nsid": "68221479@N00", "username": "RB PhotoVisions", "realname": "Robert Bonsels", "favedate": "1476177312", "iconserver": "7109", "iconfarm": 8, "contact": 0, "friend": 0, "family": 0}, {"nsid": "125148179@N02", "username": "Holger Losekann", "realname": "Holger Losekann", "favedate": "1465074685", "iconserver": "8578", "iconfarm": 9, "contact": 0, "friend": 0, "family": 0}, {"nsid": "53276435@N07", "username": "UnderTheSun1", "realname": "", "favedate": "1465028300", "iconserver": "7376", "iconfarm": 8, "contact": 0, "friend": 0, "family": 0}, {"nsid": "67875282@N07", "username": "grizzleur", "realname": "Christian Stops", "favedate": "1464687218", "iconserver": "284", "iconfarm": 1, "contact": 0, "friend": 0, "family": 0}], "faves": 139}, "stat": "ok"}, {"photo": {"id": "30127119574", "secret": "3fd2e1d8de", "server": "5823", "farm": 6, "owner": {"nsid": "126576977@N07", "username": "Pfalzknipser", "realname": "", "iconserver": "1494", "iconfarm": 2}, "title": {"_content": "Blick von Burg Lindelbrunn"}, "views": "1456", "comments": {"_content": "3"}, "tags": {"tag": [{"id": "126555647-30127119574-40955", "raw": "Landschaft", "_content": "landschaft"}, {"id": "126555647-30127119574-207600", "raw": "Lindelbrunn", "_content": "lindelbrunn"}, {"id": "126555647-30127119574-3839", "raw": "Nebel", "_content": "nebel"}, {"id": "126555647-30127119574-20100", "raw": "SW", "_content": "sw"}]}, "favpersons": [{"nsid": "41624676@N08", "username": "Knipsbildchenknipser", "realname": "Jochen Petry", "favedate": "1521813484", "iconserver": "7359", "iconfarm": 8, "contact": 0, "friend": 0, "family": 0}, {"nsid": "135973733@N07", "username": "benjamin.burr", "realname": "Benjamin Burr", "favedate": "1518034600", "iconserver": "5632", "iconfarm": 6, "contact": 0, "friend": 0, "family": 0}, {"nsid": "144695820@N07", "username": "Thorsten Burkard", "realname": "", "favedate": "1517852748", "iconserver": "5465", "iconfarm": 6, "contact": 0, "friend": 0, "family": 0}, {"nsid": "47134714@N04", "username": "fossiled", "realname": "Ed", "favedate": "1516917856", "iconserver": "7584", "iconfarm": 8, "contact": 0, "friend": 0, "family": 0}, {"nsid": "56979821@N02", "username": "chasingthelight10", "realname": "Stuart Gordon", "favedate": "1516910474", "iconserver": "3739", "iconfarm": 4, "contact": 0, "friend": 0, "family": 0}, {"nsid": "45275993@N07", "username": "GOLDFOCUS", "realname": "", "favedate": "1514930469", "iconserver": "4070", "iconfarm": 5, "contact": 0, "friend": 0, "family": 0}, {"nsid": "98282428@N07", "username": "Steinkreisphoto", "realname": "J\u00fcrgen L\u00fcno", "favedate": "1510941582", "iconserver": "0", "iconfarm": 0, "contact": 0, "friend": 0, "family": 0}, {"nsid": "154806086@N06", "username": "Gimmeldingen_Palatinate", "realname": "Michael Gall", "favedate": "1505125504", "iconserver": "4407", "iconfarm": 5, "contact": 0, "friend": 0, "family": 0}, {"nsid": "151156570@N04", "username": "saajlas", "realname": "Sasha Pekaz", "favedate": "1503211031", "iconserver": "4300", "iconfarm": 5, "contact": 0, "friend": 0, "family": 0}, {"nsid": "142658312@N02", "username": "angelika.kart", "realname": "Angelika Kart", "favedate": "1499536701", "iconserver": "4478", "iconfarm": 5, "contact": 0, "friend": 0, "family": 0}], "faves": 46}, "stat": "ok"}, {"photo": {"id": "27382133881", "secret": "fd2173d9d5", "server": "7498", "farm": 8, "owner": {"nsid": "126576977@N07", "username": "Pfalzknipser", "realname": "", "iconserver": "1494", "iconfarm": 2}, "title": {"_content": "Kloster Maulbronn"}, "views": "1121", "comments": {"_content": "1"}, "tags": {"tag": [{"id": "126555647-27382133881-79422", "raw": "Kloster", "_content": "kloster"}, {"id": "126555647-27382133881-3936072", "raw": "Lichtstimmung", "_content": "lichtstimmung"}, {"id": "126555647-27382133881-833961", "raw": "Maulbronn", "_content": "maulbronn"}]}, "favpersons": [{"nsid": "41624676@N08", "username": "Knipsbildchenknipser", "realname": "Jochen Petry", "favedate": "1521813958", "iconserver": "7359", "iconfarm": 8, "contact": 0, "friend": 0, "family": 0}, {"nsid": "96484828@N07", "username": "Marinetta2013", "realname": "marinetta montepilli", "favedate": "1467287070", "iconserver": "4192", "iconfarm": 5, "contact": 0, "friend": 0, "family": 0}, {"nsid": "82667223@N00", "username": "Brahmdev Singh", "realname": "SaT>NaRaYaN>", "favedate": "1466727105", "iconserver": "4700", "iconfarm": 5, "contact": 0, "friend": 0, "family": 0}, {"nsid": "119048804@N05", "username": "bonnaudthomas", "realname": "Thomas Bonnaud", "favedate": "1465137920", "iconserver": "5471", "iconfarm": 6, "contact": 0, "friend": 0, "family": 0}, {"nsid": "60289916@N02", "username": "RJT11", "realname": "", "favedate": "1465105840", "iconserver": "7325", "iconfarm": 8, "contact": 0, "friend": 0, "family": 0}, {"nsid": "96480691@N03", "username": "blasjaz", "realname": "", "favedate": "1465075097", "iconserver": "7751", "iconfarm": 8, "contact": 0, "friend": 0, "family": 0}, {"nsid": "125148179@N02", "username": "Holger Losekann", "realname": "Holger Losekann", "favedate": "1465074564", "iconserver": "8578", "iconfarm": 9, "contact": 0, "friend": 0, "family": 0}, {"nsid": "139302943@N08", "username": "peregrinaalemana", "realname": "", "favedate": "1465072035", "iconserver": "4769", "iconfarm": 5, "contact": 0, "friend": 0, "family": 0}, {"nsid": "124651179@N08", "username": "elisabeth.mcghee", "realname": "Elisabeth McGhee", "favedate": "1465068837", "iconserver": "668", "iconfarm": 1, "contact": 0, "friend": 0, "family": 0}, {"nsid": "128634888@N04", "username": "ki_mon_str", "realname": "Moni Strawcorner", "favedate": "1465045099", "iconserver": "8532", "iconfarm": 9, "contact": 0, "friend": 0, "family": 0}], "faves": 10}, "stat": "ok"}]